{
  "timestep_0": {
    "Ego0": {
      "position": {
        "x": -204.745,
        "y": 10.204,
        "z": -222.994
      },
      "rotation": {
        "x": 359.984,
        "y": 172.436,
        "z": -0.0
      },
      "velocity": {
        "x": 0.019,
        "y": -0.001,
        "z": -0.139
      },
      "angular_velocity": {
        "x": 0.006,
        "y": 0.002,
        "z": 0.001
      }
    },
    "NPC0": {
      "position": {
        "x": -199.518,
        "y": 10.31,
        "z": -275.085
      },
      "rotation": {
        "x": 0.0,
        "y": 171.01,
        "z": 0.0
      },
      "velocity": {
        "x": 0.0,
        "y": 0.0,
        "z": 0.0
      },
      "angular_velocity": {
        "x": 0.0,
        "y": 0.0,
        "z": 0.0
      }
    }
  },
  "timestep_1": {
    "Ego0": {
      "position": {
        "x": -204.681,
        "y": 10.204,
        "z": -223.473
      },
      "rotation": {
        "x": 359.799,
        "y": 172.418,
        "z": -0.001
      },
      "velocity": {
        "x": 0.25,
        "y": -0.0,
        "z": -1.87
      },
      "angular_velocity": {
        "x": 0.005,
        "y": -0.001,
        "z": 0.001
      }
    },
    "NPC0": {
      "position": {
        "x": -199.395,
        "y": 10.298,
        "z": -275.72
      },
      "rotation": {
        "x": 0.01,
        "y": 168.263,
        "z": -0.0
      },
      "velocity": {
        "x": 0.487,
        "y": -0.007,
        "z": -2.365
      },
      "angular_velocity": {
        "x": 0.001,
        "y": -0.065,
        "z": -0.0
      }
    }
  },
  "timestep_2": {
    "Ego0": {
      "position": {
        "x": -204.49,
        "y": 10.204,
        "z": -224.892
      },
      "rotation": {
        "x": 359.837,
        "y": 172.368,
        "z": -0.002
      },
      "velocity": {
        "x": 0.467,
        "y": 0.0,
        "z": -3.466
      },
      "angular_velocity": {
        "x": -0.004,
        "y": -0.002,
        "z": -0.0
      }
    },
    "NPC0": {
      "position": {
        "x": -198.987,
        "y": 10.298,
        "z": -277.553
      },
      "rotation": {
        "x": 0.004,
        "y": 166.927,
        "z": 0.0
      },
      "velocity": {
        "x": 1.282,
        "y": 0.0,
        "z": -5.536
      },
      "angular_velocity": {
        "x": -0.0,
        "y": -0.035,
        "z": -0.0
      }
    }
  },
  "timestep_3": {
    "Ego0": {
      "position": {
        "x": -204.217,
        "y": 10.204,
        "z": -226.91
      },
      "rotation": {
        "x": 359.935,
        "y": 172.291,
        "z": -0.003
      },
      "velocity": {
        "x": 0.577,
        "y": 0.0,
        "z": -4.237
      },
      "angular_velocity": {
        "x": -0.005,
        "y": -0.003,
        "z": -0.001
      }
    },
    "NPC0": {
      "position": {
        "x": -198.079,
        "y": 10.298,
        "z": -281.327
      },
      "rotation": {
        "x": -0.001,
        "y": 166.102,
        "z": 0.0
      },
      "velocity": {
        "x": 2.138,
        "y": -0.0,
        "z": -8.658
      },
      "angular_velocity": {
        "x": -0.0,
        "y": -0.026,
        "z": -0.0
      }
    }
  },
  "timestep_4": {
    "Ego0": {
      "position": {
        "x": -203.919,
        "y": 10.204,
        "z": -229.082
      },
      "rotation": {
        "x": 359.971,
        "y": 172.198,
        "z": -0.004
      },
      "velocity": {
        "x": 0.615,
        "y": -0.0,
        "z": -4.46
      },
      "angular_velocity": {
        "x": 0.0,
        "y": -0.003,
        "z": 0.0
      }
    },
    "NPC0": {
      "position": {
        "x": -196.919,
        "y": 10.298,
        "z": -285.983
      },
      "rotation": {
        "x": -0.001,
        "y": 165.968,
        "z": -0.0
      },
      "velocity": {
        "x": 2.379,
        "y": 0.0,
        "z": -9.518
      },
      "angular_velocity": {
        "x": 0.0,
        "y": 0.089,
        "z": -0.0
      }
    }
  },
  "timestep_5": {
    "Ego0": {
      "position": {
        "x": -203.56,
        "y": 10.204,
        "z": -231.662
      },
      "rotation": {
        "x": 359.847,
        "y": 172.076,
        "z": 359.994
      },
      "velocity": {
        "x": 0.818,
        "y": -0.001,
        "z": -5.842
      },
      "angular_velocity": {
        "x": 0.005,
        "y": -0.005,
        "z": 0.001
      }
    },
    "NPC0": {
      "position": {
        "x": -195.706,
        "y": 10.298,
        "z": -290.845
      },
      "rotation": {
        "x": -0.001,
        "y": 165.963,
        "z": -0.0
      },
      "velocity": {
        "x": 2.42,
        "y": 0.0,
        "z": -9.68
      },
      "angular_velocity": {
        "x": 0.0,
        "y": 0.104,
        "z": -0.0
      }
    }
  },
  "timestep_6": {
    "Ego0": {
      "position": {
        "x": -203.132,
        "y": 10.204,
        "z": -234.693
      },
      "rotation": {
        "x": 359.953,
        "y": 171.922,
        "z": 359.991
      },
      "velocity": {
        "x": 0.894,
        "y": 0.0,
        "z": -6.258
      },
      "angular_velocity": {
        "x": 0.004,
        "y": -0.005,
        "z": 0.001
      }
    },
    "NPC0": {
      "position": {
        "x": -194.485,
        "y": 10.298,
        "z": -295.74
      },
      "rotation": {
        "x": -0.001,
        "y": 165.957,
        "z": 0.0
      },
      "velocity": {
        "x": 2.426,
        "y": 0.0,
        "z": -9.698
      },
      "angular_velocity": {
        "x": 0.0,
        "y": 0.126,
        "z": -0.0
      }
    }
  }
}